{
  "tournamentId": "401811941",
  "year": 2026,
  "source": "parsed ESPN player scorecards",
  "holeCount": 18,
  "holes": [
    {
      "holeNumber": 1,
      "holeName": "Tea Olive",
      "par": 4,
      "yards": 445,
      "avgScore": 4.179,
      "eagles": 0,
      "birdies": 30,
      "pars": 182,
      "bogeys": 74,
      "doubles": 4,
      "other": 0,
      "avgToPar": 0.179
    },
    {
      "holeNumber": 2,
      "holeName": "Pink Dogwood",
      "par": 5,
      "yards": 585,
      "avgScore": 4.707,
      "eagles": 5,
      "birdies": 111,
      "pars": 148,
      "bogeys": 17,
      "doubles": 8,
      "other": 1,
      "avgToPar": -0.293
    },
    {
      "holeNumber": 3,
      "holeName": "Flowering Peach",
      "par": 4,
      "yards": 350,
      "avgScore": 3.9,
      "eagles": 1,
      "birdies": 74,
      "pars": 173,
      "bogeys": 37,
      "doubles": 5,
      "other": 0,
      "avgToPar": -0.1
    },
    {
      "holeNumber": 4,
      "holeName": "Flowering Crab Apple",
      "par": 3,
      "yards": 240,
      "avgScore": 3.224,
      "eagles": 0,
      "birdies": 25,
      "pars": 186,
      "bogeys": 68,
      "doubles": 11,
      "other": 0,
      "avgToPar": 0.224
    },
    {
      "holeNumber": 5,
      "holeName": "Magnolia",
      "par": 4,
      "yards": 495,
      "avgScore": 4.297,
      "eagles": 0,
      "birdies": 15,
      "pars": 178,
      "bogeys": 93,
      "doubles": 4,
      "other": 0,
      "avgToPar": 0.297
    },
    {
      "holeNumber": 6,
      "holeName": "Juniper",
      "par": 3,
      "yards": 180,
      "avgScore": 3.131,
      "eagles": 1,
      "birdies": 28,
      "pars": 195,
      "bogeys": 64,
      "doubles": 2,
      "other": 0,
      "avgToPar": 0.131
    },
    {
      "holeNumber": 7,
      "holeName": "Pampas",
      "par": 4,
      "yards": 450,
      "avgScore": 4.152,
      "eagles": 2,
      "birdies": 39,
      "pars": 172,
      "bogeys": 67,
      "doubles": 10,
      "other": 0,
      "avgToPar": 0.152
    },
    {
      "holeNumber": 8,
      "holeName": "Yellow Jasmine",
      "par": 5,
      "yards": 570,
      "avgScore": 4.624,
      "eagles": 8,
      "birdies": 109,
      "pars": 159,
      "bogeys": 12,
      "doubles": 2,
      "other": 0,
      "avgToPar": -0.376
    },
    {
      "holeNumber": 9,
      "holeName": "Carolina Cherry",
      "par": 4,
      "yards": 460,
      "avgScore": 4.003,
      "eagles": 0,
      "birdies": 51,
      "pars": 191,
      "bogeys": 44,
      "doubles": 4,
      "other": 0,
      "avgToPar": 0.003
    },
    {
      "holeNumber": 10,
      "holeName": "Camellia",
      "par": 4,
      "yards": 495,
      "avgScore": 4.166,
      "eagles": 0,
      "birdies": 38,
      "pars": 175,
      "bogeys": 68,
      "doubles": 9,
      "other": 0,
      "avgToPar": 0.166
    },
    {
      "holeNumber": 11,
      "holeName": "White Dogwood",
      "par": 4,
      "yards": 520,
      "avgScore": 4.293,
      "eagles": 0,
      "birdies": 17,
      "pars": 186,
      "bogeys": 73,
      "doubles": 13,
      "other": 1,
      "avgToPar": 0.293
    },
    {
      "holeNumber": 12,
      "holeName": "Golden Bell",
      "par": 3,
      "yards": 155,
      "avgScore": 3.152,
      "eagles": 0,
      "birdies": 41,
      "pars": 185,
      "bogeys": 48,
      "doubles": 12,
      "other": 4,
      "avgToPar": 0.152
    },
    {
      "holeNumber": 13,
      "holeName": "Azalea",
      "par": 5,
      "yards": 545,
      "avgScore": 4.762,
      "eagles": 7,
      "birdies": 110,
      "pars": 134,
      "bogeys": 28,
      "doubles": 8,
      "other": 3,
      "avgToPar": -0.238
    },
    {
      "holeNumber": 14,
      "holeName": "Chinese Fir",
      "par": 4,
      "yards": 440,
      "avgScore": 4.01,
      "eagles": 1,
      "birdies": 51,
      "pars": 184,
      "bogeys": 52,
      "doubles": 2,
      "other": 0,
      "avgToPar": 0.01
    },
    {
      "holeNumber": 15,
      "holeName": "Firethorn",
      "par": 5,
      "yards": 550,
      "avgScore": 4.855,
      "eagles": 4,
      "birdies": 96,
      "pars": 148,
      "bogeys": 29,
      "doubles": 9,
      "other": 4,
      "avgToPar": -0.145
    },
    {
      "holeNumber": 16,
      "holeName": "Redbud",
      "par": 3,
      "yards": 170,
      "avgScore": 2.952,
      "eagles": 0,
      "birdies": 65,
      "pars": 181,
      "bogeys": 37,
      "doubles": 7,
      "other": 0,
      "avgToPar": -0.048
    },
    {
      "holeNumber": 17,
      "holeName": "Nandina",
      "par": 4,
      "yards": 450,
      "avgScore": 4.238,
      "eagles": 0,
      "birdies": 22,
      "pars": 188,
      "bogeys": 69,
      "doubles": 11,
      "other": 0,
      "avgToPar": 0.238
    },
    {
      "holeNumber": 18,
      "holeName": "Holly",
      "par": 4,
      "yards": 465,
      "avgScore": 4.214,
      "eagles": 0,
      "birdies": 34,
      "pars": 169,
      "bogeys": 79,
      "doubles": 7,
      "other": 1,
      "avgToPar": 0.214
    }
  ],
  "generatedAt": "2026-04-17T01:03:06.850Z"
}
